sbmodelr.py
sbmodelr-1.2.dist-info/METADATA
sbmodelr-1.2.dist-info/WHEEL
sbmodelr-1.2.dist-info/entry_points.txt
sbmodelr-1.2.dist-info/top_level.txt
sbmodelr-1.2.dist-info/RECORD
