Metadata-Version: 2.4
Name: sbmodelr
Version: 1.2
Author-email: Pedro Mendes <pmendes@uchc.edu>
Project-URL: Repository, https://github.com/copasi/model_replicator
Project-URL: Issues, https://github.com/copasi/model_replicator/issues
Requires-Dist: copasi-basico
